{
  "cp2_eval_cp2_scenario_7.quatex": {
    "scheck cmd": "maude-hcs scheck --test=/Users/jkhoury/Documents/Research/BBN/weirdnets/code/maude-hcs-fresh/use-cases/challenge-problem-2/cp2_scenarios/cp2_scenario_7.maude --query=/Users/jkhoury/Documents/Research/BBN/weirdnets/code/maude-hcs-fresh/smc/cp2_eval_cp2_scenario_7.quatex --format json -j 0 -n 300-300 --dump /Users/jkhoury/Documents/Research/BBN/weirdnets/code/maude-hcs-fresh/results/cp2_scenario_7",
    "smc": {
      "nsims": 300,
      "queries": [
        {
          "mean": 167.31887656095626,
          "std": 16.280678399341756,
          "radius": 1.8497858096637918,
          "nsims": 300,
          "discarded": 0,
          "measure": "eval E[Latency()] with delta = 2 ;",
          "PoD": 1.0
        },
        {
          "mean": 360.48457841423226,
          "std": 38.21165652297824,
          "radius": 4.34155004270644,
          "nsims": 300,
          "discarded": 0,
          "measure": "eval E[Goodput()] with delta = 2 ;",
          "PoD": 1.0
        },
        {
          "mean": 2.256666666666667,
          "std": 0.4742064896980999,
          "radius": 0.05387861697025412,
          "nsims": 300,
          "discarded": 0,
          "measure": "eval E[ExfilFilesC2()];",
          "PoD": 1.0
        },
        {
          "mean": 2.986666666666667,
          "std": 0.664299028716789,
          "radius": 0.07547664087163826,
          "nsims": 300,
          "discarded": 0,
          "measure": "eval E[ExfilFilesC8()];",
          "PoD": 1.0
        },
        {
          "mean": 1.5766666666666667,
          "std": 0.5643733514453244,
          "radius": 0.06412323806470901,
          "nsims": 300,
          "discarded": 0,
          "measure": "eval E[ExfilFilesMA1()];",
          "PoD": 1.0
        },
        {
          "mean": 88.22729559159473,
          "std": 7.711618682864022,
          "radius": 0.8761823346179967,
          "nsims": 300,
          "discarded": 0,
          "measure": "eval E[OpDurationC2()];",
          "PoD": 1.0
        },
        {
          "mean": 112.49190683390397,
          "std": 9.942356136188073,
          "radius": 1.1296353164305486,
          "nsims": 300,
          "discarded": 0,
          "measure": "eval E[OpDurationC8()];",
          "PoD": 1.0
        },
        {
          "mean": 65.73328342874575,
          "std": 10.073090861715693,
          "radius": 1.1444891962369983,
          "nsims": 300,
          "discarded": 0,
          "measure": "eval E[OpDurationMA1()];",
          "PoD": 1.0
        }
      ]
    },
    "serial": "24.37 seconds"
  }
}